{
  "0": {
    "basicblocks": 1,
    "calls": "11 11 4 3 1 8 9",
    "file": "myproject.cpp",
    "fileloc": 7,
    "instructions": 3992,
    "name": "myproject",
    "total_instructions": 191352
  },
  "1": {
    "basicblocks": 1121,
    "calls": "",
    "file": "nnet_hept.h",
    "fileloc": 150,
    "instructions": 35921,
    "loads": {
      "G": 32,
      "L": 272
    },
    "name": "mask_and_normalize<ap_fixed<13, 4, AP_RND_CONV, AP_SAT, 0>, ap_fixed<13, 4, AP_RND_CONV, AP_SAT, 0>, config5>",
    "stores": {
      "L": 256
    },
    "total_instructions": 35921
  },
  "10": {
    "basicblocks": 33,
    "calls": "",
    "file": "nnet_dense_latency.h",
    "fileloc": 13,
    "instructions": 1587,
    "loads": {
      "L": 274
    },
    "name": "dense_latency<ap_fixed<13, 4, AP_RND_CONV, AP_SAT, 0>, ap_fixed<13, 4, AP_RND_CONV, AP_SAT, 0>, config5_dense>",
    "stores": {
      "L": 2
    },
    "total_instructions": 1587
  },
  "11": {
    "basicblocks": 1,
    "calls": "12 12 12 12 12 12 12 12 12 12 12 12 12 12 12 12 12 12 12 12 12 12 12 12 12 12 12 12 12 12 12 12 12 12 12 12 12 12 12 12 12 12 12 12 12 12 12 12 12 12 12 12 12 12 12 12 12 12 12 12 12 12 12 12 12 12 12 12 12 12 12 12 12 12 12 12 12 12 12 12 12 12 12 12 12 12 12 12 12 12 12 12 12 12 12 12 12 12 12 12 12 12 12 12 12 12 12 12 12 12 12 12 12 12 12 12 12 12 12 12 12 12 12 12 12 12 12 12",
    "file": "nnet_transpose.h",
    "fileloc": 29,
    "instructions": 641,
    "loads": {
      "L": 128
    },
    "name": "transpose<ap_fixed<13, 4, AP_RND_CONV, AP_SAT, 0>, ap_fixed<13, 4, AP_RND_CONV, AP_SAT, 0>, config5_transpose_qk>",
    "stores": {
      "L": 128
    },
    "total_instructions": 2433
  },
  "12": {
    "basicblocks": 1,
    "calls": "",
    "file": "nnet_transpose.h",
    "fileloc": 18,
    "instructions": 14,
    "name": "transfer_idx<config5_transpose_qk>",
    "total_instructions": 14
  },
  "13": {
    "basicblocks": 1,
    "calls": "",
    "file": "nnet_transpose.h",
    "fileloc": 18,
    "instructions": 14,
    "name": "transfer_idx<config5_transpose_v>",
    "total_instructions": 14
  },
  "2": {
    "basicblocks": 1,
    "calls": "",
    "file": "nnet_transpose.h",
    "fileloc": 18,
    "instructions": 14,
    "name": "transfer_idx<config5_transpose_output>",
    "total_instructions": 14
  },
  "3": {
    "basicblocks": 3329,
    "calls": "",
    "file": "nnet_hept.h",
    "fileloc": 90,
    "instructions": 93185,
    "loads": {
      "G": 256,
      "L": 256
    },
    "name": "pairwise_dist_sq_rbf<ap_fixed<13, 4, AP_RND_CONV, AP_SAT, 0>, ap_fixed<13, 4, AP_RND_CONV, AP_SAT, 0>, config5>",
    "stores": {
      "L": 256
    },
    "total_instructions": 93185
  },
  "4": {
    "basicblocks": 1,
    "calls": "13 13 13 13 13 13 13 13 13 13 13 13 13 13 13 13 13 13 13 13 13 13 13 13 13 13 13 13 13 13 13 13 13 13 13 13 13 13 13 13 13 13 13 13 13 13 13 13 13 13 13 13 13 13 13 13 13 13 13 13 13 13 13 13",
    "file": "nnet_transpose.h",
    "fileloc": 29,
    "instructions": 321,
    "loads": {
      "L": 64
    },
    "name": "transpose<ap_fixed<13, 4, AP_RND_CONV, AP_SAT, 0>, ap_fixed<13, 4, AP_RND_CONV, AP_SAT, 0>, config5_transpose_v>",
    "stores": {
      "L": 64
    },
    "total_instructions": 1217
  },
  "5": {
    "basicblocks": 33,
    "calls": "",
    "file": "nnet_dense_latency.h",
    "fileloc": 13,
    "instructions": 1587,
    "loads": {
      "L": 274
    },
    "name": "dense_latency<ap_fixed<13, 4, AP_RND_CONV, AP_SAT, 0>, ap_fixed<13, 4, AP_RND_CONV, AP_SAT, 0>, config5_dense>",
    "stores": {
      "L": 2
    },
    "total_instructions": 1587
  },
  "6": {
    "basicblocks": 33,
    "calls": "",
    "file": "nnet_dense_latency.h",
    "fileloc": 13,
    "instructions": 1587,
    "loads": {
      "L": 274
    },
    "name": "dense_latency<ap_fixed<13, 4, AP_RND_CONV, AP_SAT, 0>, ap_fixed<13, 4, AP_RND_CONV, AP_SAT, 0>, config5_dense>",
    "stores": {
      "L": 2
    },
    "total_instructions": 1587
  },
  "7": {
    "basicblocks": 33,
    "calls": "",
    "file": "nnet_dense_latency.h",
    "fileloc": 13,
    "instructions": 1587,
    "loads": {
      "L": 274
    },
    "name": "dense_latency<ap_fixed<13, 4, AP_RND_CONV, AP_SAT, 0>, ap_fixed<13, 4, AP_RND_CONV, AP_SAT, 0>, config5_dense>",
    "stores": {
      "L": 2
    },
    "total_instructions": 1587
  },
  "8": {
    "basicblocks": 1,
    "calls": "6 6 6 6 6 6 6 6 5 5 5 5 5 5 5 5 7 7 7 7 7 7 7 7 10 10 10 10 10 10 10 10",
    "file": "nnet_hept.h",
    "fileloc": 207,
    "instructions": 170,
    "loads": {
      "L": 64
    },
    "name": "bmm<ap_fixed<13, 4, AP_RND_CONV, AP_SAT, 0>, ap_fixed<13, 4, AP_RND_CONV, AP_SAT, 0>, config5>",
    "stores": {
      "L": 66
    },
    "total_instructions": 50954
  },
  "9": {
    "basicblocks": 1,
    "calls": "2 2 2 2 2 2 2 2 2 2 2 2 2 2 2 2 2 2 2 2 2 2 2 2 2 2 2 2 2 2 2 2 2 2 2 2 2 2 2 2 2 2 2 2 2 2 2 2 2 2 2 2 2 2 2 2 2 2 2 2 2 2 2 2",
    "file": "nnet_transpose.h",
    "fileloc": 29,
    "instructions": 321,
    "loads": {
      "L": 64
    },
    "name": "transpose<ap_fixed<13, 4, AP_RND_CONV, AP_SAT, 0>, ap_fixed<13, 4, AP_RND_CONV, AP_SAT, 0>, config5_transpose_output>",
    "stores": {
      "L": 64
    },
    "total_instructions": 1217
  }
}