{
    "1": {
        "name": "transpose<ap_fixed,ap_fixed<13,4,4,0,0>,config5_transpose_output>",
        "file": "firmware\/nnet_utils\/nnet_transpose.h",
        "fileloc": "35",
        "instructions": "129",
        "total_instructions": "129",
        "calls": "",
        "basicblocks": "1"
    },
    "0": {
        "name": "myproject",
        "file": "myproject.cpp",
        "fileloc": "7",
        "instructions": "1506",
        "total_instructions": "40721",
        "calls": "5 5 3 4 10 9 1",
        "basicblocks": "1"
    },
    "2": {
        "name": "dense_latency<ap_fixed<13, 4, 4, 0, 0>, ap_fixed<13, 4, 4, 0, 0>, config5_dense>.2",
        "file": "firmware\/nnet_utils\/nnet_dense_latency.h",
        "fileloc": "13",
        "instructions": "848",
        "total_instructions": "848",
        "calls": "",
        "basicblocks": "1"
    },
    "3": {
        "name": "transpose<ap_fixed,ap_fixed<13,4,4,0,0>,config5_transpose_v>",
        "file": "firmware\/nnet_utils\/nnet_transpose.h",
        "fileloc": "35",
        "instructions": "129",
        "total_instructions": "129",
        "calls": "",
        "basicblocks": "1"
    },
    "4": {
        "name": "pairwise_dist_sq_rbf<ap_fixed,ap_fixed<13,4,4,0,0>,config5>",
        "file": "firmware\/nnet_utils\/nnet_hept.h",
        "fileloc": "122",
        "instructions": "18753",
        "total_instructions": "18753",
        "calls": "",
        "basicblocks": "1",
        "loads": {
            "G": "64"
        }
    },
    "5": {
        "name": "transpose<ap_fixed,ap_fixed<13,4,4,0,0>,config5_transpose_qk>",
        "file": "firmware\/nnet_utils\/nnet_transpose.h",
        "fileloc": "35",
        "instructions": "193",
        "total_instructions": "193",
        "calls": "",
        "basicblocks": "1"
    },
    "6": {
        "name": "dense_latency<ap_fixed<13, 4, 4, 0, 0>, ap_fixed<13, 4, 4, 0, 0>, config5_dense>.1",
        "file": "firmware\/nnet_utils\/nnet_dense_latency.h",
        "fileloc": "13",
        "instructions": "848",
        "total_instructions": "848",
        "calls": "",
        "basicblocks": "1"
    },
    "7": {
        "name": "dense_latency<ap_fixed<13, 4, 4, 0, 0>, ap_fixed<13, 4, 4, 0, 0>, config5_dense>.3",
        "file": "firmware\/nnet_utils\/nnet_dense_latency.h",
        "fileloc": "13",
        "instructions": "848",
        "total_instructions": "848",
        "calls": "",
        "basicblocks": "1"
    },
    "8": {
        "name": "dense_latency<ap_fixed<13, 4, 4, 0, 0>, ap_fixed<13, 4, 4, 0, 0>, config5_dense>",
        "file": "firmware\/nnet_utils\/nnet_dense_latency.h",
        "fileloc": "13",
        "instructions": "848",
        "total_instructions": "848",
        "calls": "",
        "basicblocks": "1"
    },
    "9": {
        "name": "bmm<ap_fixed<13, 4, 4, 0, 0>, ap_fixed<13, 4, 4, 0, 0>, config5>",
        "file": "firmware\/nnet_utils\/nnet_hept.h",
        "fileloc": "227",
        "instructions": "273",
        "total_instructions": "13841",
        "calls": "8 8 8 8 6 6 6 6 2 2 2 2 7 7 7 7",
        "basicblocks": "1"
    },
    "10": {
        "name": "mask_and_normalize<ap_fixed<13, 4, 4, 0, 0>, ap_fixed<13, 4, 4, 0, 0>, config5>",
        "file": "firmware\/nnet_utils\/nnet_hept.h",
        "fileloc": "168",
        "instructions": "5977",
        "total_instructions": "5977",
        "calls": "",
        "basicblocks": "1",
        "loads": {
            "G": "16"
        }
    }
}
